py_cppstd/__init__.py
py_cppstd/exceptions.py
py_cppstd/main.py
py_cppstd/std/__init__.py
py_cppstd/std/iodirect.py
py_cppstd/std/ios.py
py_cppstd/std/ios_base.py
py_cppstd/std/iostream.py
py_cppstd/std/make_depend.py
py_cppstd/std/redir_std.py
py_cppstd-0.3.3.dist-info/LICENSE.txt
py_cppstd-0.3.3.dist-info/METADATA
py_cppstd-0.3.3.dist-info/WHEEL
py_cppstd-0.3.3.dist-info/top_level.txt
py_cppstd-0.3.3.dist-info/RECORD
