Metadata-Version: 2.1
Name: py_cppstd
Version: 0.3.3
Summary: Use C++ std::iostream style output
Home-page: https://github.com/Chinese-Cyq20100313/py_cppstd
Author: Cyan_Changes
Author-email: 1491326171@qq.com
Maintainer: Cyan_Changes
Maintainer-email: 1491326171@qq.com
License: Apache 2.0
Platform: all
Classifier: Development Status :: 4 - Beta
Classifier: Programming Language :: Python :: 3
Classifier: License :: OSI Approved :: Apache Software License
Classifier: Operating System :: OS Independent
Classifier: Programming Language :: Python :: Implementation :: CPython
Requires: executing
Requires: objprint
License-File: LICENSE.txt
